dtmf_table/__init__.pyi
dtmf_table/_dtmf_table.cpython-314-x86_64-linux-gnu.so
dtmf_table/init.py
dtmf_table-1.1.2.dist-info/METADATA
dtmf_table-1.1.2.dist-info/WHEEL
dtmf_table-1.1.2.dist-info/licenses/LICENSE
dtmf_table-1.1.2.dist-info/RECORD
