Metadata-Version: 2.4
Name: dtmf-table
Version: 1.1.2
Classifier: Development Status :: 5 - Production/Stable
Classifier: Intended Audience :: Developers
Classifier: License :: OSI Approved :: MIT License
Classifier: Programming Language :: Python :: 3
Classifier: Programming Language :: Python :: 3.8
Classifier: Programming Language :: Python :: 3.9
Classifier: Programming Language :: Python :: 3.10
Classifier: Programming Language :: Python :: 3.11
Classifier: Programming Language :: Python :: 3.12
Classifier: Programming Language :: Rust
Classifier: Topic :: Multimedia :: Sound/Audio
Classifier: Topic :: Software Development :: Libraries :: Python Modules
Classifier: Topic :: Communications :: Telephony
Requires-Dist: pytest>=6.0 ; extra == 'dev'
Requires-Dist: maturin>=1.0,<2.0 ; extra == 'dev'
Requires-Dist: myst-parser>=3.0.1 ; extra == 'dev'
Requires-Dist: sphinx>=4.0 ; extra == 'dev'
Requires-Dist: sphinx-copybutton>=0.5.2 ; extra == 'dev'
Requires-Dist: sphinx-rtd-theme>=3.1.0 ; extra == 'dev'
Requires-Dist: sphinx-autobuild>=2021.3.14 ; extra == 'dev'
Requires-Dist: pytest>=6.0 ; extra == 'test'
Provides-Extra: dev
Provides-Extra: test
License-File: LICENSE
Summary: A zero-heap, Rust backed, const-first DTMF keypad frequency table with runtime tolerance helpers.
Keywords: dtmf,telephony,audio,no_std,const
Home-Page: https://github.com/jmg049/dtmf_table
Author-email: Jack Geraghty <jgeraghty049@gmail.com>
License-Expression: MIT
Requires-Python: >=3.8
Project-URL: documentation, https://docs.rs/dtmf_table
Project-URL: homepage, https://github.com/jmg049/dtmf_table
Project-URL: python documentation, https://jmg049.github.io/dtmf_table/
Project-URL: repository, https://github.com/jmg049/dtmf_table
